PIcleaner/__init__.py
PIcleaner/cleaner.py
PIcleaner/picleaner_tests.py
PIcleaner/__pycache__/__init__.cpython-38.pyc
PIcleaner/__pycache__/cleaner.cpython-38.pyc
PIcleaner/__pycache__/picleaner_test.cpython-38-pytest-6.1.1.pyc
PIcleaner-1.3.2.dist-info/METADATA
PIcleaner-1.3.2.dist-info/WHEEL
PIcleaner-1.3.2.dist-info/top_level.txt
PIcleaner-1.3.2.dist-info/RECORD
