Metadata-Version: 2.1
Name: PIcleaner
Version: 1.3.2
Summary: Clean the dirty things in our lovely data.
Home-page: UNKNOWN
Author: Martin Kirilov, Dung Le (Eric)
Author-email: martin.kirilov@pandoraintelligence.com, dung.le@pandoraintelligence.com
License: Pandora Intelligence
Platform: UNKNOWN
Requires-Dist: clean-text[gpl]
Requires-Dist: lxml
